fcapacity_management/__init__.py
fcapacity_management/capacity_status.py
fcapacity_management/operation.py
fcapacity_management-2.4.dist-info/METADATA
fcapacity_management-2.4.dist-info/WHEEL
fcapacity_management-2.4.dist-info/top_level.txt
fcapacity_management-2.4.dist-info/RECORD
