Metadata-Version: 2.1
Name: fcapacity_management
Version: 2.4
Requires-Dist: azure-identity
Requires-Dist: azure-mgmt-resource
